oslo_reports/__init__.py
oslo_reports/_i18n.py
oslo_reports/_utils.py
oslo_reports/guru_meditation_report.py
oslo_reports/opts.py
oslo_reports/report.py
oslo_reports/generators/__init__.py
oslo_reports/generators/conf.py
oslo_reports/generators/process.py
oslo_reports/generators/threading.py
oslo_reports/generators/version.py
oslo_reports/locale/en_GB/LC_MESSAGES/oslo_reports.po
oslo_reports/models/__init__.py
oslo_reports/models/base.py
oslo_reports/models/conf.py
oslo_reports/models/process.py
oslo_reports/models/threading.py
oslo_reports/models/version.py
oslo_reports/models/with_default_views.py
oslo_reports/tests/__init__.py
oslo_reports/tests/test_base_report.py
oslo_reports/tests/test_guru_meditation_report.py
oslo_reports/tests/test_openstack_generators.py
oslo_reports/tests/test_views.py
oslo_reports/views/__init__.py
oslo_reports/views/jinja_view.py
oslo_reports/views/json/__init__.py
oslo_reports/views/json/generic.py
oslo_reports/views/text/__init__.py
oslo_reports/views/text/generic.py
oslo_reports/views/text/header.py
oslo_reports/views/text/process.py
oslo_reports/views/text/threading.py
oslo_reports/views/xml/__init__.py
oslo_reports/views/xml/generic.py
oslo_reports-3.7.0.dist-info/licenses/AUTHORS
oslo_reports-3.7.0.dist-info/licenses/LICENSE
oslo_reports-3.7.0.dist-info/METADATA
oslo_reports-3.7.0.dist-info/WHEEL
oslo_reports-3.7.0.dist-info/entry_points.txt
oslo_reports-3.7.0.dist-info/pbr.json
oslo_reports-3.7.0.dist-info/top_level.txt
oslo_reports-3.7.0.dist-info/RECORD
