Metadata-Version: 2.4
Name: oslo.reports
Version: 3.7.0
Summary: oslo.reports library
Author-email: OpenStack <openstack-discuss@lists.openstack.org>
Project-URL: Homepage, https://docs.openstack.org/oslo.reports
Project-URL: Repository, https://opendev.org/openstack/oslo.reports
Classifier: Environment :: OpenStack
Classifier: Intended Audience :: Information Technology
Classifier: Intended Audience :: System Administrators
Classifier: License :: OSI Approved :: Apache Software License
Classifier: Operating System :: POSIX :: Linux
Classifier: Programming Language :: Python
Classifier: Programming Language :: Python :: 3
Classifier: Programming Language :: Python :: 3.10
Classifier: Programming Language :: Python :: 3.11
Classifier: Programming Language :: Python :: 3.12
Classifier: Programming Language :: Python :: 3.13
Classifier: Programming Language :: Python :: 3 :: Only
Classifier: Programming Language :: Python :: Implementation :: CPython
Requires-Python: >=3.10
License-File: LICENSE
License-File: AUTHORS
Requires-Dist: pbr>=2.0.0
Requires-Dist: Jinja2>=2.10
Requires-Dist: oslo.serialization>=2.18.0
Requires-Dist: psutil>=3.2.2
Requires-Dist: oslo.i18n>=3.15.3
Requires-Dist: oslo.utils>=3.33.0
Requires-Dist: oslo.config>=5.1.0
Provides-Extra: greenlet
Requires-Dist: greenlet>=0.4.15; extra == "greenlet"
Dynamic: license-file
Dynamic: requires-dist
